{"additions": 1170, "auther_ref": "add_hcal_depth_clustering", "auther_sha": "6ac171ca4084eb9aefdbcd319e0d459c58334e53", "author": "lgray", "body": "Checkpoint of present tuning work for the shashlik.\n", "branch": "CMSSW_6_2_X_SLHC", "changed_files": 26, "closed_at": "1414012960", "comments": 13, "commits": 14, "created_at": "1413438364", "deletions": 128, "labels": ["comparison-pending", "fastsim-pending", "operations-pending", "orp-pending", "pending-signatures", "reconstruction-pending", "simulation-pending", "tests-pending"], "merge_commit_sha": "0a20c9a86819b0ad56333b61a64cc5149544d4da", "merged_at": "1414012960", "merged_by": "cmsbuild", "milestone": "Next CMSSW_6_2_X_SLHC", "number": 5845, "release-notes": [], "review_comments": 0, "state": "closed", "title": "HCAL Depth Clustering for SLHC, everything up to now.", "updated_at": "1414012960", "user": "lgray"}