{"additions": 78, "auther_ref": "13_2_X-inputsource-checks", "auther_sha": "dbc336ab796c4476d4da332ff5a09e086312cef0", "author": "smorovic", "body": "#### PR description:\r\n\r\nImproved file size limit checks in input sources. Print more debug info when waiting for a buffer.\r\n\r\n#### PR validation:\r\n\r\nRetested in DAQ test cluster and covered also by unit tests.\r\n", "branch": "master", "changed_files": 4, "comments": 3, "commits": 2, "created_at": "1685470365", "deletions": 42, "labels": ["daq-pending", "pending-signatures", "tests-pending", "orp-pending", "code-checks-approved"], "milestone": "CMSSW_13_2_X", "number": 41814, "release-notes": [], "review_comments": 0, "state": "open", "title": "[DAQ] improved file size/buffer size checks in DAQ input source (13_2_X)", "updated_at": "1685471422", "user": "smorovic"}