{"additions": 5, "auther_ref": "unittest-fix", "auther_sha": "1e4e71868feae5aaf4725570ded8f5814c01cc0b", "author": "igv4321", "body": "#### PR description:\r\n\r\nPurely technical update of a unit test, will not affect any workflows. Avoiding raw channel id comparison in the unit test of the database dump, as these ids can change.\r\n\r\n#### PR validation:\r\n\r\nUnit test was successfully run.\r\n", "branch": "master", "changed_files": 1, "comments": 0, "commits": 1, "created_at": "1699379120", "deletions": 1, "labels": ["db-pending", "pending-signatures", "tests-pending", "orp-pending", "code-checks-pending"], "milestone": "CMSSW_14_0_X", "number": 43220, "release-notes": [], "review_comments": 0, "state": "open", "title": "Ignoring raw channel ids in the unit test database dump comparison", "updated_at": "1699379145", "user": "igv4321"}