{"additions": 35, "auther_ref": "GEM-onlineDQM_update_211124-12_2_X", "auther_sha": "26d49852e8068c0c46201a2019b12e9519bacf41", "author": "quark2", "body": "#### PR description:\r\nOn PR #36230 @perrotta pointed a lot of stuff which are not suitable for the CMSSW convention and buggy, but unfortunately, the PR merged without the fix on the comments. This is the hotfix.\r\n\r\n#### PR validation:\r\nTests are done and one can check again by `runTheMatrix` workflows\r\n\r\n@jshlee @watson-ij ", "branch": "master", "changed_files": 4, "comments": 0, "commits": 1, "created_at": "1637859454", "deletions": 29, "labels": ["dqm-pending", "pending-signatures", "tests-pending", "orp-pending", "code-checks-pending"], "milestone": "CMSSW_12_2_X", "number": 36253, "release-notes": [], "review_comments": 0, "state": "open", "title": "Modification on r-phi distribution plots and fix on under/overflow bins in GEM onlineDQM (continue)", "updated_at": "1637859475", "user": "quark2"}