{"additions": 910, "auther_ref": "TICLNanoAOD_CMSSW_15_1_X_2025-07-06-2300", "auther_sha": "0a94a52e93286fdcf03f8293d1e4b77cb9a45145", "author": "waredjeb", "body": "This PR adds TICL objects to the NanoAOD HLT output. Reco-objects (Tracksters, TICLCandidates, and SuperClusters) are added to the NanoAOD baseline. Sim-objects (SimTracksters, SimTICLCandidates) and association maps are added to the `hltNanoValCustomize`  only.\r\n\r\nThe `readNano.py` under `tests` has been updated for testing the new collections.\r\n\r\nTested on 29634.772", "branch": "master", "changed_files": 12, "comments": 4, "commits": 1, "created_at": "1751969229", "deletions": 80, "labels": ["hlt-pending", "pending-signatures", "tests-pending", "orp-pending", "code-checks-approved", "xpog-pending"], "milestone": "CMSSW_15_1_X", "number": 48500, "release-notes": [], "review_comments": 0, "state": "open", "title": "TICL Objects in HLT NanoAOD", "updated_at": "1751969869", "user": "waredjeb"}