{"additions": 1824, "auther_ref": "duplicated_clusters_bugfix-slhc17p2", "auther_sha": "f6d7641979571bfdd5b1f34c45740eeff1daf113", "author": "venturia", "body": "This pull request includes a bug fix and a few changes in an analysis package\n", "branch": "CMSSW_6_2_X_SLHC", "changed_files": 8, "closed_at": "1414487875", "comments": 11, "commits": 9, "created_at": "1413723243", "deletions": 47, "labels": ["analysis-pending", "comparison-pending", "orp-pending", "pending-signatures", "reconstruction-pending", "tests-approved"], "merge_commit_sha": "8426d83fc408cb0db25595eb3d81e5af5d631c8e", "merged_at": "1414487875", "merged_by": "cmsbuild", "milestone": "Next CMSSW_6_2_X_SLHC", "number": 5889, "release-notes": [], "review_comments": 4, "state": "closed", "title": "Bug fix to avoid duplicated clusters on the same track in upgraded FPIX", "updated_at": "1434178495", "user": "venturia"}