{"additions": 111, "auther_ref": "from-CMSSW_11_2_X_2020-06-04-1100-update-GEM-valid-pad-clusters", "auther_sha": "f60d38f913a8696eee1c44f0d48ba8923f1909be", "author": "dildick", "body": "#### PR description:\r\n\r\nUpdate valid condition for GEM pads and clusters according to [DN-20-016, page 28](https://gitlab.cern.ch/tdr/notes/DN-20-016/blob/master/temp/DN-20-016_temp.pdf). In short: ME0 pad 255, GE1/1 pad 255 and GE2/1 pad 511 are considered invalid. This PR also fixes a minor bug in the GEM-CSC trigger that excluded GE1/1 or GE2/1 zero pads.\r\n\r\n#### PR validation:\r\n\r\nTested with WF 27434.0\r\n\r\n#### if this PR is a backport please specify the original PR and why you need to backport that PR:\r\n\r\nN/A\r\n\r\n@jshlee @hyunyong ", "branch": "master", "changed_files": 9, "closed_at": "1592837171", "comments": 47, "commits": 1, "created_at": "1591290769", "deletions": 44, "labels": ["code-checks-approved", "comparison-available", "fully-signed", "l1-approved", "orp-approved", "simulation-approved", "tests-approved", "upgrade-approved"], "merge_commit_sha": "3a4abd517d91580bb7a2dbb614587cd7589950c0", "merged_at": "1592837171", "merged_by": "cmsbuild", "milestone": "CMSSW_11_2_X", "number": 30115, "release-notes": [], "review_comments": 10, "state": "closed", "title": "Update valid condition for GEM pads and clusters", "updated_at": "1592837171", "user": "dildick"}