{"additions": 5, "auther_ref": "alca-JERC_UL16_106X", "auther_sha": "4e16ec7eae758a048cdf63d54d1473ee78caf1da", "author": "malbouis", "body": "#### PR description:\r\n\r\nThis PR is to update the Run 2 offline data and MC Global Tags with the jet energy resolution and corrections for the UL16 MiniAODv2 production.\r\n\r\nThe tags were updated according to this request: https://hypernews.cern.ch/HyperNews/CMS/get/calibrations/4401.html\r\n\r\nGT differences:\r\n\r\n**2016 realistic pre-VFP era**\r\nhttps://cms-conddb.cern.ch/cmsDbBrowser/diff/Prod/gts/106X_mcRun2_asymptotic_preVFP_v10/106X_mcRun2_asymptotic_preVFP_v11\r\n\r\n**2016 realistic post-VFP era**\r\nhttps://cms-conddb.cern.ch/cmsDbBrowser/diff/Prod/gts/106X_mcRun2_asymptotic_v16/106X_mcRun2_asymptotic_v17\r\n\r\n**Offline data**\r\nhttps://cms-conddb.cern.ch/cmsDbBrowser/diff/Prod/gts/106X_dataRun2_v33/106X_dataRun2_v35\r\n\r\n**Offline data relval**\r\nhttps://cms-conddb.cern.ch/cmsDbBrowser/diff/Prod/gts/106X_dataRun2_relval_v31/106X_dataRun2_relval_v33\r\n\r\n\r\n#### PR validation:\r\n\r\nrunTheMatrix.py -l limited,136.772,136.783,136.852 --ibeos\r\n\r\n#### if this PR is a backport please specify the original PR and why you need to backport that PR:\r\n\r\nThis PR is not a backport but it will be forward ported to master.\r\n", "branch": "CMSSW_10_6_X", "changed_files": 1, "closed_at": "1622068375", "comments": 17, "commits": 2, "created_at": "1620822026", "deletions": 5, "labels": ["alca-approved", "fully-signed", "orp-approved", "tests-approved"], "merge_commit_sha": "9a1c1926b8c559fb84f9417dd927c6053b398a26", "merged_at": "1622068375", "merged_by": "cmsbuild", "milestone": "CMSSW_10_6_X", "number": 33710, "release-notes": [], "review_comments": 0, "state": "closed", "title": "Update of JERC tags for UL16", "updated_at": "1622068376", "user": "malbouis"}