{"additions": 4, "auther_ref": "newME0PreDigiParameters", "auther_sha": "060cdfef911ee6ae5ffb472bbf139b8f8a932c67", "author": "calabria", "body": "This change will allow us to change the ME0 space and time resolution by simply re-digitizing the existing samples once they are produced. We would like to have this simple change in pre13 and son then in 810.\n@kpedro88 @pietverwilligen @jshlee @mmaggi \n", "branch": "CMSSW_8_1_X", "changed_files": 1, "closed_at": "1476538680", "comments": 20, "commits": 4, "created_at": "1475820425", "deletions": 4, "labels": ["comparison-available", "fully-signed", "orp-approved", "simulation-approved", "tests-approved"], "merge_commit_sha": "747d6e6aa827bad44e3de4dca992586090ecfc37", "merged_at": "1476538680", "merged_by": "cmsbuild", "milestone": "Next CMSSW_8_1_X", "number": 16132, "release-notes": [], "review_comments": 0, "state": "closed", "title": "New ME0PreDigi parameters", "updated_at": "1480626923", "user": "calabria"}