{"additions": 1, "auther_ref": "assertInMethodSetter", "auther_sha": "0dd3f38bac8677964a68260728e7eede92b0d86e", "author": "Dr15Jones", "body": "#### PR description:\r\n\r\nThe exception has been happening while using RNTuple. Switch to assert to allow us to trigger cmsRun's thread tracebacks when the problem occurs.\r\n\r\nThis is meant to help us debug the threading problem seen in the IBs.\r\n\r\n#### PR validation:\r\nCode compiles.\r\n\r\nresolves https://github.com/cms-sw/framework-team/issues/1393", "branch": "CMSSW_15_1_RNTUPLE_X", "changed_files": 1, "comments": 12, "commits": 1, "created_at": "1747223326", "deletions": 0, "labels": ["reconstruction-approved", "fully-signed", "tests-approved", "orp-pending", "code-checks-approved", "tests-manual-override"], "number": 48078, "release-notes": [], "review_comments": 0, "state": "open", "title": "Add assert to MethodSetter to trigger traceback", "updated_at": "1747252502", "user": "Dr15Jones"}