{"additions": 2, "auther_ref": "root-update-v6-12-00-patches-20180403", "auther_sha": "4fe52cf04e105cfdb0b5c05740c53165a645f037", "author": "mrodozov", "body": "", "branch": "IB/CMSSW_10_2_X/root612", "changed_files": 1, "closed_at": "1522989277", "comments": 7, "commits": 1, "created_at": "1522760516", "deletions": 2, "labels": ["externals-pending", "orp-pending", "pending-signatures", "tests-approved"], "merge_commit_sha": "cfe5f71168144790efb8c7b141fcce98d3e5a39c", "merged_at": "1522989277", "merged_by": "smuzaffar", "number": 3893, "release-notes": [], "review_comments": 0, "state": "closed", "title": "Updated root to tip of branch v6-12-00-patches", "updated_at": "1522989277", "user": "mrodozov"}