{"additions": 110, "auther_ref": "consumesMigration1", "auther_sha": "5738132165356d61475d87b8afcfbbb54dd30a85", "author": "deguio", "body": "consumes migration for a bunch of remaining packages and code cleanup. more will come.\n", "branch": "CMSSW_7_1_X", "changed_files": 57, "closed_at": "1394621580", "comments": 10, "commits": 3, "created_at": "1394188709", "deletions": 833, "labels": ["dqm-approved", "fully-signed", "generators-approved", "geometry-approved", "tests-approved"], "merge_commit_sha": "f02a16c43a2e64dc1b0d969007fb93b4234a95a2", "merged_at": "1394621580", "merged_by": "nclopezo", "milestone": "CMSSW_7_1_0_pre5", "number": 2763, "release-notes": [], "review_comments": 0, "state": "closed", "title": "Consumes migration1", "updated_at": "1394621580", "user": "deguio"}