{"additions": 5, "auther_ref": "EventGenerationFailure10", "auther_sha": "989bd471119e5284f5304f32029be00170a63507", "author": "perrozzi", "body": "to catch missing or exceeding LHE events", "branch": "master", "changed_files": 3, "closed_at": "1510909641", "comments": 21, "commits": 2, "created_at": "1510835990", "deletions": 2, "labels": ["code-checks-approved", "comparison-available", "core-approved", "fully-signed", "generators-approved", "orp-approved", "tests-started"], "merge_commit_sha": "734d41830c7a18998e87810ff17cd89550645b59", "merged_at": "1510909641", "merged_by": "cmsbuild", "milestone": "CMSSW_10_0_X", "number": 21328, "release-notes": [], "review_comments": 0, "state": "closed", "title": "add EventGenerationFailure exit code ", "updated_at": "1510909641", "user": "perrozzi"}