{"additions": 185, "auther_ref": "add-py3-torch", "auther_sha": "60cf19573d720e664eca1dcdf27b9df82e09afd2", "author": "cms-sw", "body": "", "branch": "IB/CMSSW_13_1_X/master", "changed_files": 6, "comments": 34, "commits": 13, "created_at": "1678910834", "deletions": 0, "labels": ["externals-pending", "pending-signatures", "tests-started", "orp-pending"], "number": 8388, "release-notes": [], "review_comments": 3, "state": "open", "title": "Add recipe for py3-torch", "updated_at": "1679299354", "user": "iarspider"}