{"additions": 1, "auther_ref": "rucio-1236", "auther_sha": "5e11ff0bb05d4ab7f336bb32ae260dd1bfb5a731", "author": "amaltaro", "body": "Besides the WMCor eco-system, it has an impact on the CRAB TaskWorker too. FYI @belforte \r\nRelease notes: https://github.com/rucio/rucio/releases", "branch": "comp_gcc630", "changed_files": 1, "closed_at": "1600177834", "comments": 4, "commits": 1, "created_at": "1600167928", "deletions": 1, "labels": [], "merge_commit_sha": "d29bea152a25806bdf023142104a23451778f665", "merged_at": "1600177834", "merged_by": "muhammadimranfarooqi", "number": 6240, "release-notes": [], "review_comments": 0, "state": "closed", "title": "Bump rucio-clients to version 1.23.6", "updated_at": "1600177834", "user": "amaltaro"}