{"additions": 3, "auther_ref": "Prof2Update", "auther_sha": "8195b76dbadcb5f4be7cbe36f516c8f21616d3ec", "author": "intrepid42", "body": "Need to specify `LIBDIR` to find `libProfessor2.so`. Also updated to 2.2.2 then.", "branch": "IB/CMSSW_10_5_X/gcc700", "changed_files": 2, "closed_at": "1549356287", "comments": 11, "commits": 2, "created_at": "1548867135", "deletions": 2, "labels": ["externals-approved", "fully-signed", "orp-approved", "tests-approved"], "merge_commit_sha": "391b36b909376f926469272ea131f99f6d36018f", "merged_at": "1549356287", "merged_by": "cmsbuild", "number": 4668, "release-notes": [], "review_comments": 0, "state": "closed", "title": "Fix Professor2 and update to 2.2.2", "updated_at": "1549356287", "user": "intrepid42"}