{"additions": 13, "auther_ref": "reconstruction-llvm16-warn3", "auther_sha": "ed5f7dfec04566441226532f397716bc512a4aa1", "author": "aandvalenzuela", "body": "Fixes set but unused warnings from clang-16 in CLANG IBs", "branch": "master", "changed_files": 42, "comments": 3, "commits": 3, "created_at": "1683206335", "deletions": 183, "labels": ["reconstruction-pending", "pending-signatures", "orp-pending", "tests-started", "code-checks-approved", "tracking", "trk"], "milestone": "CMSSW_13_2_X", "number": 41543, "release-notes": [], "review_comments": 0, "state": "open", "title": "[RECONSTRUCTION] [CLANG] Fix warnings reported by llvm16 in CLANG IBs", "updated_at": "1683206823", "user": "aandvalenzuela"}