{"additions": 185, "auther_ref": "newCentMast", "auther_sha": "7df7b1ba9104744f89d49d9e47f07cebe2d21043", "author": "bundocka", "body": "New centrality tuning.", "branch": "master", "changed_files": 2, "closed_at": "1543323711", "comments": 20, "commits": 2, "created_at": "1542628350", "deletions": 0, "labels": ["code-checks-approved", "comparison-available", "fully-signed", "l1-approved", "orp-approved", "tests-approved"], "merge_commit_sha": "b6b485dbfbec4d0ff72c710321c95344520578fa", "merged_at": "1543323711", "merged_by": "cmsbuild", "milestone": "CMSSW_10_4_X", "number": 25279, "release-notes": [], "review_comments": 0, "state": "closed", "title": "L1TCalo: Add new caloParams with updated HI centrality v1_4_1", "updated_at": "1543323711", "user": "bundocka"}