{"additions": 30, "auther_ref": "dd-store-lock", "auther_sha": "8fbe2ee9ef554507b925aae8377340a1943db8f4", "author": "ianna", "body": "* Lock the Stores when asked to do so\r\n* Add a DDCompactView constructor which allows to unlock the Stores. \r\n\r\nNote: The only use case where the Stores need to be unlocked is the MagneticField geometry producer.\r\n\r\nThis is a new PR is based on https://github.com/cms-sw/cmssw/pull/24355 and addresses https://github.com/cms-sw/cmssw/pull/24355#discussion_r211944953", "branch": "master", "changed_files": 5, "closed_at": "1535630876", "comments": 44, "commits": 6, "created_at": "1535025480", "deletions": 51, "labels": ["code-checks-approved", "comparison-available", "fully-signed", "geometry-approved", "orp-approved", "reconstruction-approved", "tests-approved"], "merge_commit_sha": "c6eda536e9298a697b281514ae5a9a3e6ab79312", "merged_at": "1535630876", "merged_by": "cmsbuild", "milestone": "CMSSW_10_3_X", "number": 24378, "release-notes": [], "review_comments": 0, "state": "closed", "title": "DD Store Lock", "updated_at": "1535630876", "user": "ianna"}