{"additions": 1, "auther_ref": "smuzaffar-patch-9", "auther_sha": "98e2af5bcd07e6a8f216050f7600d3419365baa9", "author": "cms-sw", "body": "There is bug in build rules and `<flags EDM_PLUGIN=\"0\"/>` in `plugins/BuildFile.xml` still generate a plugin instead of a shared library. New build rule shoudl fix this. \r\n\r\nCurrently we do not have any `plugins/BuildFile.xml` setting `<flags EDM_PLUGIN=\"0\"/>` , so this fix should not break any thing", "branch": "IB/CMSSW_12_0_X/master", "changed_files": 1, "closed_at": "1624388542", "comments": 6, "commits": 1, "created_at": "1624370838", "deletions": 1, "labels": ["externals-approved", "fully-signed", "orp-pending", "tests-approved"], "merge_commit_sha": "c7c2bd50ba3c5e433027fc36c8a792c00b010959", "merged_at": "1624388542", "merged_by": "smuzaffar", "number": 7055, "release-notes": [], "review_comments": 0, "state": "closed", "title": "[BuildRules] Fix the EDM_PLUGIN=\"0\" flag in plugisn/BuildFile", "updated_at": "1624391863", "user": "smuzaffar"}