{"additions": 22, "auther_ref": "add_missing_json_dependency", "auther_sha": "4ad57ad0c52280453a998e3ad97a703e8939f1a6", "author": "fwyzard", "body": "#### PR description:\r\n\r\nAdd missing dependencies on the `json` external.\r\n\r\n#### PR validation:\r\n\r\nNone.\r\n", "branch": "master", "changed_files": 4, "comments": 12, "commits": 1, "created_at": "1762013349", "deletions": 18, "labels": ["l1-pending", "alca-approved", "pending-signatures", "tests-approved", "orp-pending", "db-approved", "bug-fix", "code-checks-approved"], "milestone": "CMSSW_16_0_X", "number": 49278, "release-notes": [], "review_comments": 1, "state": "open", "title": "Add missing dependencies on json", "updated_at": "1762188144", "user": "fwyzard"}