{"additions": 3, "auther_ref": "CMSSW_7_2_X_2014-08-20-0200/fix720pre4assert-conversionOneLeg", "auther_sha": "fe57c40d6999a84e3538c3dd2b43cc382e72814b", "author": "slava77", "body": "seedCollection needs to be reset to zero on a legal exit from the method, otherwise next call will give an assert\n\nshould fix crashes reported in https://hypernews.cern.ch/HyperNews/CMS/get/relval/3121.html\nTested with  http://cms-project-relval.web.cern.ch/cms-project-relval/failures/CMSSW_7_2_0_pre4/standard/WElSkim2012D__RelVal_wEl2012D_Job1.tar.gz \n", "branch": "CMSSW_7_2_X", "changed_files": 1, "closed_at": "1408644109", "comments": 8, "commits": 1, "created_at": "1408628966", "deletions": 3, "labels": ["comparison-pending", "fully-signed", "reconstruction-approved", "tests-pending"], "merge_commit_sha": "16ac91e2de2b72dea2e573223968d5bd0b39ced5", "merged_at": "1408644109", "merged_by": "davidlange6", "milestone": "Next CMSSW_7_2_X", "number": 5022, "release-notes": [], "review_comments": 0, "state": "closed", "title": "fix crash in pre4 Assertion `seedCollection==nullptr' failed.", "updated_at": "1408648003", "user": "slava77"}