{"additions": 221, "auther_ref": "fix_inclusion_guards_RecoTracker", "auther_sha": "e88c62600ca3e74a13f91c93a9425dd90d6361dc", "author": "mmusich", "body": "#### PR description:\r\n\r\nTitle says it all, addresses second part of the https://github.com/cms-sw/cmssw/pull/41058#issuecomment-1473531611 , to comply with http://cms-sw.github.io/cms_coding_rules.html#4--technical-coding-rules-1\r\n\r\n#### PR validation:\r\n\r\n`cmssw` compiles.\r\nTechnical, no regressions expected.\r\n\r\n#### If this PR is a backport please specify the original PR and why you need to backport that PR. If this PR will be backported please specify to which release cycle the backport is meant for:\r\n\r\nN/A", "branch": "master", "changed_files": 99, "closed_at": "1681467064", "comments": 7, "commits": 1, "created_at": "1681190311", "deletions": 221, "labels": ["reconstruction-approved", "fully-signed", "tests-approved", "orp-approved", "code-checks-approved", "tracking"], "merge_commit_sha": "eb13b0d57836d6aa006b174e63941db0ae7fc420", "merged_at": "1681467064", "merged_by": "cmsbuild", "milestone": "CMSSW_13_1_X", "number": 41310, "release-notes": [], "review_comments": 0, "state": "closed", "title": "fix `RecoTracker/Pixel*` subsystems header file inclusions guards to comply with cmssw rule 4.1", "updated_at": "1681467090", "user": "mmusich"}