{"additions": 7, "auther_ref": "update_alpaka_1.2.0", "auther_sha": "5c8f48104d85501abea9ad47053a9fce648bcae1", "author": "fwyzard", "body": "#### PR description:\r\n\r\n  - Update the signature of `allocMappedBuf` for alpaka 1.2.0\r\n\r\n#### PR validation:\r\n\r\nNone.\r\n\r\n#### If this PR will be backported please specify to which release cycle the backport is meant for:\r\n\r\nNot to be backported.", "branch": "master", "changed_files": 2, "comments": 2, "commits": 1, "created_at": "1737095498", "deletions": 7, "labels": ["pending-signatures", "tests-pending", "orp-pending", "code-checks-rejected", "heterogeneous-pending"], "milestone": "CMSSW_15_0_X", "number": 47119, "release-notes": [], "review_comments": 0, "state": "open", "title": "Update CMSSW for alpaka 1.2.0", "updated_at": "1737095683", "user": "fwyzard"}