{"additions": 9, "auther_ref": "RevertHWW", "auther_sha": "aae2530b78b49334fad12c3b1d890d5094622f6a", "author": "deguio", "body": "", "branch": "CMSSW_7_5_X", "changed_files": 4, "closed_at": "1435682513", "comments": 11, "commits": 2, "created_at": "1435580682", "deletions": 5, "labels": ["comparison-available", "dqm-approved", "fully-signed", "tests-approved"], "merge_commit_sha": "ab66d6e3e877208dfc63efa8e7fb448b883f4d98", "merged_at": "1435682512", "merged_by": "cmsbuild", "milestone": "CMSSW_7_5_X", "number": 9954, "release-notes": [], "review_comments": 0, "state": "closed", "title": "Revert hww", "updated_at": "1435682513", "user": "deguio"}