{"additions": 556, "auther_ref": "moduleCentricTracer", "auther_sha": "28cbcbd218ea3b6f0586ee22cc7e24050e4e5061", "author": "Dr15Jones", "body": "\r\n#### PR description:\r\n\r\nImproved UI in the viewer.\r\nAdded unit tests.\r\n\r\n#### PR validation:\r\n\r\nCode was tested with HLT tracer log output.", "branch": "master", "changed_files": 5, "closed_at": "1702052304", "comments": 14, "commits": 1, "created_at": "1701884304", "deletions": 190, "labels": ["core-approved", "fully-signed", "tests-approved", "orp-approved", "code-checks-approved"], "merge_commit_sha": "b047ff77a167a7592250addaae6f6fe4178ccc35", "merged_at": "1702052304", "merged_by": "cmsbuild", "milestone": "CMSSW_14_0_X", "number": 43514, "release-notes": [], "review_comments": 2, "state": "closed", "title": "Add module centric view to Tracer viewer", "updated_at": "1702052304", "user": "Dr15Jones"}