{"additions": 96, "auther_ref": "dev_UParT_V01", "auther_sha": "447b77dc38e81c43439155a864f67fd472a4b4ea", "author": "y19y19", "body": "", "branch": "master", "changed_files": 4, "closed_at": "1743829216", "comments": 6, "commits": 2, "created_at": "1743006839", "deletions": 0, "labels": ["pending-signatures", "externals-pending", "tests-pending", "orp-approved", "reconstruction-approved"], "merge_commit_sha": "e5d4a629153e17ae35122ce831275f7e1c699cb9", "merged_at": "1743829216", "merged_by": "cmsbuild", "number": 66, "release-notes": [], "review_comments": 1, "state": "closed", "title": "change the location of UParTAK4/PUPPI/V01 model to /models/, add files for SONIC", "updated_at": "1743829218", "user": "y19y19"}