{"additions": 65, "auther_ref": "pr-rocm-tests", "auther_sha": "0e8b9ce7590451f09f22c93713223c5dbbb34f94", "author": "cms-sw", "body": "Additional changes :\r\n\r\n- [x] PR Unit test job (https://cmssdt.cern.ch/jenkins/job/ib-run-pr-unittests) - add `GPU_FLAVOR` parameter, select node based on it.\r\n\r\n- [x] PR Relval job (https://cmssdt.cern.ch/jenkins/job/ib-run-pr-relvals/) - select node based on `TEST_FLAVOR`\r\n\r\n- [ ] Monitoring job (https://cmssdt.cern.ch/jenkins/job/jenkins-monitor-queue/) needs to be changed - kill pr test jobs that are stuck due to lumi node being offline", "branch": "master", "changed_files": 5, "comments": 26, "commits": 2, "created_at": "1737552687", "deletions": 36, "labels": ["orp-pending", "pending-signatures", "externals-pending", "tests-pending"], "number": 2418, "release-notes": [], "review_comments": 6, "state": "open", "title": "Run PR gpu utests/relvals on both CUDA and ROCm GPUs", "updated_at": "1738144981", "user": "iarspider"}