{"additions": 65, "auther_ref": "add-highfive", "auther_sha": "48f94283b3aa19eaa03251be2aabc93751e54aca", "author": "cms-sw", "body": "please test\r\nResolves: https://github.com/cms-sw/cmsdist/issues/5987", "branch": "IB/CMSSW_11_2_X/master", "changed_files": 4, "closed_at": "1593438343", "comments": 25, "commits": 4, "created_at": "1593187371", "deletions": 0, "labels": ["comparison-available", "externals-approved", "fully-signed", "orp-pending", "tests-started"], "merge_commit_sha": "dd576daf28b2dd36589c8851b2265ed4a8399d8e", "merged_at": "1593438343", "merged_by": "smuzaffar", "number": 5996, "release-notes": [], "review_comments": 2, "state": "closed", "title": "Add HighFive to externals", "updated_at": "1593448017", "user": "mrodozov"}