{"additions": 19991, "auther_ref": "CPyCppyy-1.12.16", "auther_sha": "98e5eccea0e7d3befdc585ffb979f9cf46fb41fb", "author": "guitargeek", "body": "", "branch": "cms/master/4279cb9707", "changed_files": 464, "comments": 5, "commits": 35, "created_at": "1710534158", "deletions": 6072, "labels": ["orp-pending", "pending-signatures", "tests-approved", "externals-pending"], "number": 205, "release-notes": [], "review_comments": 0, "state": "open", "title": "[PyROOT] Update cppyy to a recent version", "updated_at": "1710566447", "user": "smuzaffar"}