{"additions": 513, "auther_ref": "EgPMS2Producer8X", "auther_sha": "ff2a0a81a5243dad3c26a4626dffdf8122db4cf9", "author": "Sam-Harper", "body": "Dear All,\n\nThis is the 80X edition of https://github.com/cms-sw/cmssw/pull/13846 as the HLT needs in in 80X as well\n\nCheers,\nSam\n", "branch": "CMSSW_8_0_X", "changed_files": 2, "closed_at": "1460053289", "comments": 8, "commits": 9, "created_at": "1459084126", "deletions": 0, "labels": ["comparison-available", "fully-signed", "hlt-approved", "orp-approved", "tests-approved"], "merge_commit_sha": "5f8a1f5a4b9662c7ad91d07422c7ad9c71ce3d63", "merged_at": "1460053289", "merged_by": "cmsbuild", "milestone": "CMSSW_8_0_X", "number": 13847, "release-notes": [], "review_comments": 0, "state": "closed", "title": "E/g HLT Pixel Match Variable Producer :80X edition", "updated_at": "1460053289", "user": "Sam-Harper"}