{"additions": 1, "auther_ref": "smuzaffar-patch-3-1", "auther_sha": "961db0089318e606cdd768ead337c9c9bde0f2e1", "author": "cms-sw", "body": "needed by https://github.com/cms-sw/cmssw/pull/15662\n", "branch": "IB/CMSSW_8_1_X/gcc530", "changed_files": 1, "closed_at": "1472803806", "comments": 1, "commits": 1, "created_at": "1472563606", "deletions": 1, "labels": ["externals-pending", "orp-pending", "pending-signatures", "tests-pending"], "merge_commit_sha": "4e9e3d364c0322264fdcab295f14e5993df85d48", "merged_at": "1472803806", "merged_by": "smuzaffar", "number": 2473, "release-notes": [], "review_comments": 0, "state": "closed", "title": "Update data-SLHCUpgradeSimulations-Geometry.spec", "updated_at": "1476857329", "user": "smuzaffar"}