{"additions": 1, "auther_ref": "smuzaffar-patch-2", "auther_sha": "d8967be0881ddb2a343975dfd0e03ace707bccbc", "author": "cms-externals", "body": "See details at https://github.com/cms-sw/cmssw/issues/49546#issuecomment-3817230639", "branch": "cms/master/c1d637433e3b3f9012b226c2c9125c494b470ae6", "changed_files": 1, "comments": 7, "commits": 1, "created_at": "1769700659", "deletions": 1, "labels": ["orp-pending", "pending-signatures", "tests-started", "externals-pending", "requires-external"], "number": 10, "release-notes": [], "review_comments": 0, "state": "open", "title": "Disable eigen debug for CUDA compilers too", "updated_at": "1770037518", "user": "smuzaffar"}