{"additions": 4, "auther_ref": "tf-xla-copy-fix", "auther_sha": "a4a906429d6b1acb1910a3f4630b889636693175", "author": "cms-sw", "body": "", "branch": "IB/CMSSW_17_0_X/master", "changed_files": 2, "comments": 4, "commits": 1, "created_at": "1775801812", "deletions": 2, "labels": ["tests-rejected", "externals-pending", "pending-signatures", "orp-pending"], "number": 10483, "release-notes": [], "review_comments": 0, "state": "open", "title": "fix for tensorflow-xla-runtime and relocate torch/macros.h", "updated_at": "1775802043", "user": "smuzaffar"}