{"additions": 282, "auther_ref": "build-only-v3", "auther_sha": "236d8b1cfba3aa781c38b6722c6bbf885c1fb066", "author": "cms-sw", "body": "Trying a simple way of build-only tests (follow up on https://github.com/cms-sw/cms-bot/pull/2525 )", "branch": "master", "changed_files": 24, "comments": 40, "commits": 9, "created_at": "1753160106", "deletions": 57, "labels": ["orp-pending", "pending-signatures", "externals-pending", "tests-pending"], "number": 2536, "release-notes": [], "review_comments": 6, "state": "open", "title": "Support for please build PR tests i.e. not running Relvals/Addons or other tests", "updated_at": "1753199438", "user": "smuzaffar"}