{"additions": 8, "auther_ref": "IB/CMSSW_7_4_X/next", "auther_sha": "0191f062f8a914bac0e97cb186133ae21ebd5e0a", "author": "smuzaffar", "body": "", "branch": "IB/CMSSW_7_4_X/next", "changed_files": 2, "closed_at": "1418032350", "comments": 0, "commits": 2, "created_at": "1418032336", "deletions": 1, "labels": [], "merge_commit_sha": "3672c917e61c840d5d0419ac59f8b9788353550c", "merged_at": "1418032350", "merged_by": "smuzaffar", "number": 1241, "release-notes": [], "review_comments": 0, "state": "closed", "title": "sync some more stuff for debug builds", "updated_at": "1418032351", "user": "smuzaffar"}