{"additions": 3, "auther_ref": "NJetsMC_93X", "auther_sha": "95f33a3da3259f8e6df3cb640093d45127bb4fbc", "author": "EmyrClement", "body": "Backport of #25498 ", "branch": "CMSSW_9_3_X", "changed_files": 1, "comments": 1, "commits": 1, "created_at": "1545050868", "deletions": 3, "labels": ["backport-ok", "comparison-pending", "generators-pending", "orp-pending", "pending-signatures", "tests-pending"], "milestone": "CMSSW_9_3_X", "number": 25507, "release-notes": [], "review_comments": 0, "state": "open", "title": "NJetsMC filter backport to CMSSW_9_3_X", "updated_at": "1545050923", "user": "EmyrClement"}