{"additions": 16, "auther_ref": "Run3-hcx283", "auther_sha": "9861d19e194f330cb51b7d18aab46ce4286b5453", "author": "bsunanda", "body": "#### PR description:\r\n\r\nUse ESGetToken in CalibCalorimetry/HcalPlugins\r\n\r\n#### PR validation:\r\n\r\nUse the runTheMatrix test workflows \r\n\r\n#### if this PR is a backport please specify the original PR and why you need to backport that PR:\r\n\r\nNothing special", "branch": "master", "changed_files": 7, "closed_at": "1610698706", "comments": 9, "commits": 1, "created_at": "1609869481", "deletions": 21, "labels": ["alca-approved", "code-checks-approved", "fully-signed", "orp-approved", "tests-approved"], "merge_commit_sha": "5e05de2605f92076113466d2581365a57b8e629b", "merged_at": "1610698706", "merged_by": "cmsbuild", "milestone": "CMSSW_11_3_X", "number": 32605, "release-notes": [], "review_comments": 0, "state": "closed", "title": "Run3-hcx283 Use ESGetToken in CalibCalorimetry/HcalPlugins", "updated_at": "1610698707", "user": "bsunanda"}