{"additions": 2, "auther_ref": "peruzzim-patch-1", "auther_sha": "d95d5ec989040199f14f0b0c1bd5188c18a1babf", "author": "cms-nanoAOD", "body": "#### PR description:\r\n\r\nA bugfix (wrong parenthesis usage) to address the errors in RelVal workflows recently observed in the IB https://github.com/cms-sw/cmssw/issues/28119#issuecomment-547318704\r\n\r\n#### PR validation:\r\n\r\nChecked in the cms-nanoAOD integration repository for the main workflows, will re-test here for those that were crashing.", "branch": "CMSSW_10_6_X", "changed_files": 1, "closed_at": "1572444357", "comments": 11, "commits": 1, "created_at": "1572346545", "deletions": 2, "labels": ["analysis-approved", "comparison-available", "fully-signed", "orp-approved", "tests-approved", "xpog-approved"], "merge_commit_sha": "9d8cd7a741f2abde83aec02e7ce82c94cbc9b78b", "merged_at": "1572444356", "merged_by": "cmsbuild", "milestone": "CMSSW_10_6_X", "number": 28302, "release-notes": [], "review_comments": 0, "state": "closed", "title": "Fix wrong parenthesis in era switches for UL [106X]", "updated_at": "1572458422", "user": "peruzzim"}