{"additions": 1, "auther_ref": "smuzaffar-patch-1", "auther_sha": "180636382b58a6386c69c40efe09ddbf61991aa8", "author": "cms-sw", "body": "So that it does not clash with package's default library name", "branch": "master", "changed_files": 1, "closed_at": "1526733104", "comments": 11, "commits": 1, "created_at": "1526643552", "deletions": 1, "labels": ["code-checks-approved", "comparison-available", "fully-signed", "generators-approved", "orp-approved", "tests-approved"], "merge_commit_sha": "9e1d38cf91822a28193ca7abb625c3742adc4dab", "merged_at": "1526733104", "merged_by": "cmsbuild", "milestone": "CMSSW_10_2_X", "number": 23249, "release-notes": [], "review_comments": 0, "state": "closed", "title": "Fix GeneratorInterfaceCascadeInterface plugin name", "updated_at": "1526733104", "user": "smuzaffar"}