{"additions": 2, "auther_ref": "update-DataFormats-L1ScoutingRawData-to-V00-01-00", "auther_sha": "46ffdd95a54b2ade02da17e4de8a0e7ab64d5e2a", "author": "cms-sw", "body": "Move DataFormats-L1ScoutingRawData data to new tag, see \nhttps://github.com/cms-data/DataFormats-L1ScoutingRawData/pull/1\n", "branch": "IB/CMSSW_14_0_X/master", "changed_files": 2, "closed_at": "1705677471", "comments": 4, "commits": 2, "created_at": "1705677440", "deletions": 0, "labels": ["tests-pending", "externals-approved", "fully-signed", "orp-pending"], "merge_commit_sha": "80d57fc9b6e8a6ad265bd028bea1818da57e3e2f", "merged_at": "1705677471", "merged_by": "smuzaffar", "number": 8954, "release-notes": [], "review_comments": 0, "state": "closed", "title": "Update tag for DataFormats-L1ScoutingRawData to V00-01-00", "updated_at": "1705677479", "user": "cmsbuild"}