{"additions": 1, "auther_ref": "FixTIBOverlap", "auther_sha": "8443c554f77509767bf07ccaf1e7d61053b4ae56", "author": "vargasa", "body": "#### PR description:\r\n\r\nAddresses Issue: https://github.com/cms-sw/cmssw/issues/28256 \r\n\r\n#### PR validation:\r\n\r\n`master`\r\n![master](https://user-images.githubusercontent.com/16821717/68696377-e2434680-054a-11ea-8c2f-67b569536da9.png)\r\n\r\n`master + thisPr`\r\n![thisPr](https://user-images.githubusercontent.com/16821717/68696404-ecfddb80-054a-11ea-9979-9b348ca98bb3.png)\r\n\r\n`Reference`\r\n![reference](https://user-images.githubusercontent.com/16821717/68696419-f5561680-054a-11ea-9fb6-deb77b49bee9.png)\r\n\r\nFor validation instructions please check: https://github.com/cms-sw/cmssw/pull/27689\r\n\r\n", "branch": "master", "changed_files": 1, "closed_at": "1573677384", "comments": 13, "commits": 2, "created_at": "1573577497", "deletions": 1, "labels": ["code-checks-approved", "comparison-available", "fully-signed", "geometry-approved", "orp-approved", "tests-approved"], "merge_commit_sha": "9684f6207f4bd7010558f17fd2756f497e8810a2", "merged_at": "1573677384", "merged_by": "cmsbuild", "milestone": "CMSSW_11_0_X", "number": 28386, "release-notes": [], "review_comments": 0, "state": "closed", "title": "DD4hep: Tracker TIB Algo Fix Tube Arguments", "updated_at": "1573677385", "user": "vargasa"}