{"additions": 5, "auther_ref": "HcalDetIdTransform-update", "auther_sha": "7bd5dc5ba2af7cb97d3f3c420ca7f1c99eb053d3", "author": "igv4321", "body": "This change does not affect any existing code.\nPlease check and approve quickly.\n", "branch": "CMSSW_8_1_X", "changed_files": 2, "closed_at": "1472567589", "comments": 15, "commits": 1, "created_at": "1472244714", "deletions": 0, "labels": ["alca-approved", "comparison-available", "db-approved", "fully-signed", "orp-approved", "tests-approved"], "merge_commit_sha": "dade4dcf038d30efef211e5055074c7bc440e319", "merged_at": "1472567589", "merged_by": "davidlange6", "milestone": "Next CMSSW_8_1_X", "number": 15627, "release-notes": [], "review_comments": 0, "state": "closed", "title": "A trivial modification allowing item indexing by subdetector", "updated_at": "1473749549", "user": "igv4321"}