{"additions": 33, "auther_ref": "IB/CMSSW_14_1_X/master_rocm_6.1.0", "auther_sha": "f1b8c122dd4ef8f141cb4ac6573d7e320e6360c3", "author": "fwyzard", "body": "Add amd-smi and ROCProfiler binaries and libraries.", "branch": "IB/CMSSW_14_1_X/master", "changed_files": 2, "comments": 19, "commits": 1, "created_at": "1713360019", "deletions": 20, "labels": ["tests-approved", "externals-approved", "fully-signed", "orp-pending", "requires-external", "tests-ib-failure"], "number": 9143, "release-notes": [], "review_comments": 0, "state": "open", "title": "Update ROCm to version 6.1.0", "updated_at": "1713522163", "user": "fwyzard"}