{"additions": 2, "auther_ref": "root-update-master-20241209", "auther_sha": "3c8e2de2dbee26b5cd7b6b1e011bb94ccbf0f530", "author": "iarspider", "body": "Changes [link](https://github.com/root-project/root/compare/575201eeaf...2c8521e17d) to core, ntuple and jsroot", "branch": "IB/CMSSW_15_0_X/rootmaster", "changed_files": 1, "closed_at": "1733821575", "comments": 4, "commits": 1, "created_at": "1733731391", "deletions": 2, "labels": ["tests-approved", "externals-pending", "pending-signatures", "orp-pending"], "merge_commit_sha": "bf309068e77f6d608803390cf087c104c259758e", "merged_at": "1733821574", "merged_by": "smuzaffar", "number": 9557, "release-notes": [], "review_comments": 0, "state": "closed", "title": "[ROOTMaster] Updated root to tip of branch master", "updated_at": "1733821575", "user": "iarspider"}