{"additions": 14, "auther_ref": "comp-nobuild", "auther_sha": "09db59996bc8b7b50737c33767e94ca0e385989c", "author": "amaltaro", "body": "Before merging it, a broader discussion is needed. I'm starting a thread in the WebInterfaces HN...", "branch": "comp_gcc630", "changed_files": 1, "closed_at": "1605256888", "comments": 4, "commits": 3, "created_at": "1605104149", "deletions": 11, "labels": [], "merge_commit_sha": "ec4328adbcb990515f1b49ae4ec210d7c3c0d135", "merged_at": "1605256888", "merged_by": "muhammadimranfarooqi", "number": 6405, "release-notes": [], "review_comments": 4, "state": "closed", "title": "Stop building obsolete COMP services", "updated_at": "1605256888", "user": "amaltaro"}