{"additions": 1, "auther_ref": "smuzaffar-patch-1", "auther_sha": "4df7c3d2c53ddc9d5e01148516e76415683df98a", "author": "cms-externals", "body": "", "branch": "cms/v2.6.4", "changed_files": 1, "comments": 6, "commits": 1, "created_at": "1686729505", "deletions": 1, "labels": ["orp-pending", "pending-signatures", "tests-approved", "externals-pending"], "number": 10, "release-notes": [], "review_comments": 0, "state": "open", "title": "Fix for cuda 11.8 cusolver version", "updated_at": "1686846221", "user": "smuzaffar"}