{"additions": 2, "auther_ref": "smuzaffar-patch-1", "auther_sha": "afc750c59b1403716333cbb4c5e69ba00489988b", "author": "cms-sw", "body": "", "branch": "IB/CMSSW_14_1_X/g13", "changed_files": 1, "comments": 4, "commits": 1, "created_at": "1712026875", "deletions": 2, "labels": ["tests-rejected", "externals-pending", "pending-signatures", "orp-pending"], "number": 9106, "release-notes": [], "review_comments": 0, "state": "open", "title": "[GCC13] Update to latest gcc 13 commit", "updated_at": "1712070722", "user": "smuzaffar"}