{"additions": 1040, "auther_ref": "instrument_CMSSW_for_Nvidia_nvprof_101x", "auther_sha": "62dbfe5bcb4d225b8eece7f334135de7119a05a6", "author": "fwyzard", "body": "Instrument cmssw for nvprof/nvvm\r\n  - implement a Service to provide CMSSW-aware annotations to nvprof/nvvm\r\n  - highlight selected modules and delayed modules\r\n  - update for CMSSW 10.1.x", "branch": "master", "changed_files": 2, "comments": 0, "commits": 2, "created_at": "1517218413", "deletions": 0, "labels": [], "number": 22009, "release-notes": [], "review_comments": 0, "state": "open", "title": "Instrument cmssw for nvidia nvprof/nvvm (10.1.x)", "updated_at": "1517218413", "user": "fwyzard"}