{"additions": 5842, "auther_ref": "master", "auther_sha": "d7d89e680d2d7c2c50b3eb3c43fb14d1635b38a1", "author": "dildick", "body": "@rathjd @tahuang1991\r\n\r\nStill a work in progress... ", "branch": "master", "changed_files": 171, "comments": 9, "commits": 17, "created_at": "1625094130", "deletions": 3819, "labels": ["externals-pending", "l1-pending", "orp-pending", "pending-signatures", "tests-pending"], "number": 10, "release-notes": [], "review_comments": 0, "state": "open", "title": "Add missing headers, missing columns, and missing GEM-CSC LUTs", "updated_at": "1625690520", "user": "dildick"}