{"additions": 2, "auther_ref": "root-update-master-20250929", "auther_sha": "aa891bf7568a0fc937749085ca55d4d0bb2dde34", "author": "akritkbehera", "body": "", "branch": "IB/CMSSW_16_0_X/rootmaster", "changed_files": 1, "comments": 2, "commits": 1, "created_at": "1759113200", "deletions": 2, "labels": ["tests-pending", "externals-pending", "pending-signatures", "orp-pending"], "number": 10095, "release-notes": [], "review_comments": 0, "state": "open", "title": "[ROOT6] Root update master 20250929", "updated_at": "1759113225", "user": "akritkbehera"}