{"additions": 3318, "auther_ref": "update7", "auther_sha": "20a4e128204930f47969e3fcd85a75052afea7ed", "author": "dkotlins", "body": "Small updates to test programs: new det-id, \"bytoken\" and some code cleanup.\nOnly test code affected.\n", "branch": "CMSSW_7_0_X", "changed_files": 15, "closed_at": "1385388474", "comments": 1, "commits": 8, "created_at": "1385388359", "deletions": 625, "labels": ["pending-signatures", "reconstruction-pending", "simulation-pending", "tests-pending"], "milestone": "CMSSW_7_0_0_pre9", "number": 1586, "release-notes": [], "review_comments": 0, "state": "closed", "title": "Update7", "updated_at": "1385388480", "user": "dkotlins"}