{"additions": 11, "auther_ref": "devel_revert46026_142X", "auther_sha": "d8d7ab043d9c0d9c97c689f1c8b3933265add017", "author": "missirol", "body": "backport of #47088\r\n\r\n#### PR description:\r\n\r\nFrom the description of #47088:\r\n\r\n> This PR updates the L1-uGT emulator by reverting #46026. Checks described in #46026 and #47030 show that #46026 introduced disagreements between the unpacked and emulated L1-uGT decisions for seeds using muons reconstructed in separate bunch crossings (specifically, the seed `L1_CDC_SingleMu_3_er1p2_TOP120_DPHI2p618_3p142`).\r\n\r\n#### PR validation:\r\n\r\nNone beyond the validation done for #47088.\r\n\r\n#### If this PR is a backport, please specify the original PR and why you need to backport that PR. If this PR will be backported, please specify to which release cycle the backport is meant for:\r\n\r\n#47088\r\n\r\nBugfix to the L1-uGT emulator.\r\n", "branch": "CMSSW_14_2_X", "changed_files": 4, "comments": 7, "commits": 1, "created_at": "1736698782", "deletions": 59, "labels": ["l1-approved", "fully-signed", "tests-approved", "orp-pending", "bug-fix", "backport-ok"], "milestone": "CMSSW_14_2_X", "number": 47089, "release-notes": [], "review_comments": 0, "state": "open", "title": "revert #46026 (L1-uGT emulator) [`14_2_X`]", "updated_at": "1736955422", "user": "missirol"}